tips/dateapi.pyc
tips/tips.py
tips/dateapi.py
tips/test_gen_db.py
tips/db.py
tips/stats.py
tips/__init__.pyc
tips/db.pyc
tips/__init__.py
tips/minigraph.py
tips/__pycache__/test_gen_db.cpython-27-PYTEST.pyc
tips-1.1.dist-info/DESCRIPTION.rst
tips-1.1.dist-info/WHEEL
tips-1.1.dist-info/RECORD
tips-1.1.dist-info/METADATA
tips-1.1.dist-info/metadata.json
tips-1.1.dist-info/entry_points.txt
tips-1.1.dist-info/top_level.txt
