Metadata-Version: 2.0
Name: tips
Version: 1.1
Summary: A tips per day tracker and displayer
Home-page: github.com/TiredSounds/tips
Author: TiredSounds
Author-email: tiredsounds17@gmail.com
License: UNKNOWN
Download-URL: github.com/TiredSounds/tips
Platform: UNKNOWN
Requires-Dist: backports.shutil-get-terminal-size
